Metadata-Version: 2.1
Name: popcornTimeApi
Version: 0.0.2
Summary: Unofficial python Api wrapper for Popcorntime-Api
Home-page: https://github.com/DavidM42/popcornTimeApi
Author: DavidM42
Author-email: david@merz.dev
License: MIT
Platform: UNKNOWN
Classifier: Programming Language :: Python :: 3
Classifier: License :: OSI Approved :: MIT License
Classifier: Operating System :: OS Independent
